easy_kafka/__init__.py
easy_kafka/kafka_config.py
easy_kafka/kafka_consumer.py
easy_kafka/kafka_log.py
easy_kafka/kafka_producer.py
easy_kafka-0.0.4.dist-info/METADATA
easy_kafka-0.0.4.dist-info/WHEEL
easy_kafka-0.0.4.dist-info/top_level.txt
easy_kafka-0.0.4.dist-info/RECORD
