Metadata-Version: 2.1
Name: easy-kafka
Version: 0.0.4
Summary: easy to use kafka(kb)
Home-page: https://github.com/ksust/easy_kafka
Author: ksust
Author-email: admin@ksust.com
Maintainer: ksust
Maintainer-email: admin@ksust.com
License: UNKNOWN
Platform: all
Classifier: Programming Language :: Python :: 3
Classifier: Programming Language :: Python :: 3.5
Classifier: Programming Language :: Python :: 3.6
Classifier: Programming Language :: Python :: 3.7
Classifier: Programming Language :: Python :: 3.8
Requires-Dist: kafka-python (==2.0.1)
Requires-Dist: PyYAML (==5.3.1)
